setup.cfg
setup.py
digDictionaryExtractor/__init__.py
digDictionaryExtractor/dictionary_extractor.py
digDictionaryExtractor/name_dictionary_extractor.py
digDictionaryExtractor/populate_trie.py
digDictionaryExtractor.egg-info/PKG-INFO
digDictionaryExtractor.egg-info/SOURCES.txt
digDictionaryExtractor.egg-info/dependency_links.txt
digDictionaryExtractor.egg-info/requires.txt
digDictionaryExtractor.egg-info/top_level.txt
test/test_name_extractor.py
test/test_populate_trie.py