Metadata-Version: 1.1
Name: digDictionaryExtractor
Version: 0.3.0
Summary: digDictionaryExtractor
Home-page: https://github.com/usc-isi-i2/dig-dictionary-extractor
Author: Jason Slepicka
Author-email: jasonslepicka@gmail.com
License: UNKNOWN
Download-URL: https://github.com/usc-isi-i2/dig-dictionary-extractor
Platform: UNKNOWN
